tests/__init__.py
tests/core.py
utils_plus/__init__.py
utils_plus/math.py
utils_plus/version.py
utils_plus/itertools/__init__.py
utils_plus/performance/__init__.py
utils_plus-0.0.2.dist-info/LICENSE
utils_plus-0.0.2.dist-info/METADATA
utils_plus-0.0.2.dist-info/WHEEL
utils_plus-0.0.2.dist-info/top_level.txt
utils_plus-0.0.2.dist-info/RECORD
