Metadata-Version: 2.1
Name: utils-plus
Version: 0.0.2
Summary: Useful plugins for utils.
Home-page: https://github.com/LeeKLTW/utils_plus
Author: KunLin Lee
Author-email: LeeKLTW@gmail.com
License: UNKNOWN
Platform: UNKNOWN
Requires-Python: >=3.6
